src/__init__.py
src/config.py
src/differ.py
src/utility.py
sead_data_diff-0.1.3.dist-info/METADATA
sead_data_diff-0.1.3.dist-info/WHEEL
sead_data_diff-0.1.3.dist-info/entry_points.txt
sead_data_diff-0.1.3.dist-info/RECORD
