Metadata-Version: 2.1
Name: sead-data-diff
Version: 0.1.3
Summary: 
Author: Roger Mähler
Author-email: roger.mahler@hotmail.com
Requires-Python: >=3.11,<4.0
Classifier: Programming Language :: Python :: 3
Classifier: Programming Language :: Python :: 3.11
Requires-Dist: click (>=8.1.7,<9.0.0)
Requires-Dist: data-diff (>=0.8.4,<0.9.0)
Requires-Dist: loguru (>=0.7.2,<0.8.0)
Requires-Dist: psycopg2 (>=2.9.7,<3.0.0)
Requires-Dist: python-dotenv (>=1.0.0,<2.0.0)
Requires-Dist: tqdm (>=4.66.1,<5.0.0)
